espial/__init__.py
espial/analysis.py
espial/cli.py
espial/config.py
espial/datastruct.py
espial/load.py
espial/static/force-docs.html
espial/static/force.json
espial/static/force4.js
espial/static/logo.svg
espial/static/main.css
espial/static/mvp.css
espial/templates/base.html
espial/templates/index.html
espial/templates/misc.html
espial/templates/search.html
espial/templates/show_concept.html
espial/templates/show_doc.html
espial-0.2.2.dist-info/LICENSE
espial-0.2.2.dist-info/METADATA
espial-0.2.2.dist-info/WHEEL
espial-0.2.2.dist-info/entry_points.txt
espial-0.2.2.dist-info/top_level.txt
espial-0.2.2.dist-info/RECORD
